VidToScr/MovToScrConverter.py
VidToScr/Mp4ToScrConverter.py
VidToScr/ScrToMp4Converter.py
VidToScr/__init__.py
vidtoscr-1.3.0.dist-info/licenses/LICENSE.txt
vidtoscr-1.3.0.dist-info/METADATA
vidtoscr-1.3.0.dist-info/WHEEL
vidtoscr-1.3.0.dist-info/top_level.txt
vidtoscr-1.3.0.dist-info/RECORD
