Metadata-Version: 2.4
Name: VidToScr
Version: 1.3.0
Summary: A library to convert video files to SCR format.
Author-email: Marcin Jacek Chmiel <martingonn.dev@outlook.com>
License: Apache Software License
Project-URL: homepage, https://github.com/Martingonn/VID-to-SCR-Lib
Classifier: Programming Language :: Python :: 3
Classifier: License :: OSI Approved :: Apache Software License
Classifier: Operating System :: OS Independent
Requires-Python: >=3.6
License-File: LICENSE.txt
Dynamic: license-file
